{
    "outputs": ["nl_4_output"],
    "c_layers": [
        {
            "next": "nl_0_nl",
            "rom": 1167448,
            "op_by_type": {"smul_f32_f32c4": 2324100},
            "c_forward": "forward_dense",
            "c_code_emit": true,
            "macc": 2324100,
            "name": "gemm_0",
            "c_id": 0,
            "tensors": {
                "outputs": ["gemm_0_output"],
                "inputs": ["serving_default_dense_input0_output"],
                "scratchs": [],
                "weights": [
                    "gemm_0_weights",
                    "gemm_0_bias"
                ]
            },
            "weight_sparsity": [
                3.528247493655989E-5,
                2324100,
                82
            ],
            "layer_type": "dense",
            "m_id": 0
        },
        {
            "next": "gemm_1",
            "rom": 0,
            "op_by_type": {"op_f32_f32": 1524},
            "c_forward": "forward_relu",
            "c_code_emit": true,
            "macc": 1524,
            "name": "nl_0_nl",
            "c_id": 1,
            "tensors": {
                "outputs": ["nl_0_nl_output"],
                "inputs": ["gemm_0_output"],
                "scratchs": [],
                "weights": []
            },
            "weight_sparsity": [
                0,
                1,
                0
            ],
            "layer_type": "nl",
            "m_id": 0
        },
        {
            "next": "nl_1_nl",
            "rom": 196160,
            "op_by_type": {"smul_f32_f32c4": 390400},
            "c_forward": "forward_dense",
            "c_code_emit": true,
            "macc": 390400,
            "name": "gemm_1",
            "c_id": 2,
            "tensors": {
                "outputs": ["gemm_1_output"],
                "inputs": ["nl_0_nl_output"],
                "scratchs": [],
                "weights": [
                    "gemm_1_weights",
                    "gemm_1_bias"
                ]
            },
            "weight_sparsity": [
                2.3053278688567325E-5,
                390400,
                9
            ],
            "layer_type": "dense",
            "m_id": 1
        },
        {
            "next": "gemm_2",
            "rom": 0,
            "op_by_type": {"op_f32_f32": 256},
            "c_forward": "forward_relu",
            "c_code_emit": true,
            "macc": 256,
            "name": "nl_1_nl",
            "c_id": 3,
            "tensors": {
                "outputs": ["nl_1_nl_output"],
                "inputs": ["gemm_1_output"],
                "scratchs": [],
                "weights": []
            },
            "weight_sparsity": [
                0,
                1,
                0
            ],
            "layer_type": "nl",
            "m_id": 1
        },
        {
            "next": "nl_2_nl",
            "rom": 131584,
            "op_by_type": {"smul_f32_f32": 32896},
            "c_forward": "forward_dense",
            "c_code_emit": true,
            "macc": 32896,
            "name": "gemm_2",
            "c_id": 4,
            "tensors": {
                "outputs": ["gemm_2_output"],
                "inputs": ["nl_1_nl_output"],
                "scratchs": [],
                "weights": [
                    "gemm_2_weights",
                    "gemm_2_bias"
                ]
            },
            "weight_sparsity": [
                0,
                32896,
                0
            ],
            "layer_type": "dense",
            "m_id": 2
        },
        {
            "next": "gemm_3",
            "rom": 0,
            "op_by_type": {"op_f32_f32": 128},
            "c_forward": "forward_relu",
            "c_code_emit": true,
            "macc": 128,
            "name": "nl_2_nl",
            "c_id": 5,
            "tensors": {
                "outputs": ["nl_2_nl_output"],
                "inputs": ["gemm_2_output"],
                "scratchs": [],
                "weights": []
            },
            "weight_sparsity": [
                0,
                1,
                0
            ],
            "layer_type": "nl",
            "m_id": 2
        },
        {
            "next": "nl_4",
            "rom": 6192,
            "op_by_type": {"smul_f32_f32": 1548},
            "c_forward": "forward_dense",
            "c_code_emit": true,
            "macc": 1548,
            "name": "gemm_3",
            "c_id": 6,
            "tensors": {
                "outputs": ["gemm_3_output"],
                "inputs": ["nl_2_nl_output"],
                "scratchs": [],
                "weights": [
                    "gemm_3_weights",
                    "gemm_3_bias"
                ]
            },
            "weight_sparsity": [
                0,
                1548,
                0
            ],
            "layer_type": "dense",
            "m_id": 3
        },
        {
            "next": "nl_4",
            "rom": 0,
            "op_by_type": {"op_f32_f32": 180},
            "c_forward": "forward_sm",
            "c_code_emit": true,
            "macc": 180,
            "name": "nl_4",
            "c_id": 7,
            "tensors": {
                "outputs": ["nl_4_output"],
                "inputs": ["gemm_3_output"],
                "scratchs": [],
                "weights": []
            },
            "weight_sparsity": [
                0,
                1,
                0
            ],
            "layer_type": "nl",
            "m_id": 4
        }
    ],
    "data_alignment": 4,
    "compilation_options": {
        "optimization": "balanced",
        "options": [
            "allocate-inputs",
            "allocate-outputs",
            "split-weights"
        ],
        "compression": "high"
    },
    "inputs": ["serving_default_dense_input0_output"],
    "macc": 2751032,
    "c_weights_header": 0,
    "activations_alignment": 4,
    "c_nodes_n": 8,
    "c_tensors_n": 17,
    "type": "tflite",
    "c_arrays": [
        {
            "mem_pool": "activations",
            "offset": 0,
            "is_const": false,
            "format": "float32",
            "n_items": 128,
            "tensors": [{
                "shape": [
                    1,
                    128
                ],
                "name": "nl_2_nl_output"
            }],
            "raw_fmt": "(FLOAT, 32 bit, C Size: 32 bits)",
            "c_mem_pool": "**default**",
            "padded": true,
            "size": 128,
            "c_type": "float",
            "name": "nl_2_nl_output_array",
            "c_id": 0,
            "c_bits": 32,
            "c_size_in_byte": 512
        },
        {
            "mem_pool": "activations",
            "offset": 512,
            "is_const": false,
            "format": "float32",
            "n_items": 12,
            "tensors": [{
                "shape": [
                    1,
                    12
                ],
                "name": "gemm_3_output"
            }],
            "raw_fmt": "(FLOAT, 32 bit, C Size: 32 bits)",
            "c_mem_pool": "**default**",
            "padded": true,
            "size": 12,
            "c_type": "float",
            "name": "gemm_3_output_array",
            "c_id": 1,
            "c_bits": 32,
            "c_size_in_byte": 48
        },
        {
            "mem_pool": "activations",
            "offset": 0,
            "is_const": false,
            "format": "float32",
            "n_items": 12,
            "tensors": [{
                "shape": [
                    1,
                    12
                ],
                "name": "nl_4_output"
            }],
            "raw_fmt": "(FLOAT, 32 bit, C Size: 32 bits)",
            "c_mem_pool": "**default**",
            "padded": true,
            "size": 12,
            "c_type": "float",
            "name": "nl_4_output_array",
            "c_id": 2,
            "c_bits": 32,
            "c_size_in_byte": 48,
            "io_type": "output"
        },
        {
            "mem_pool": "weights",
            "offset": 0,
            "is_const": true,
            "format": "float32",
            "n_items": 1536,
            "tensors": [{
                "shape": [
                    128,
                    12
                ],
                "name": "gemm_3_weights"
            }],
            "zeros": 0,
            "raw_fmt": "(FLOAT, 32 bit, C Size: 32 bits)",
            "c_mem_pool": "gemm_3_weights",
            "padded": true,
            "size": 1536,
            "c_type": "const float",
            "name": "gemm_3_weights_array",
            "c_id": 3,
            "c_bits": 32,
            "c_size_in_byte": 6144
        },
        {
            "mem_pool": "weights",
            "offset": 64,
            "is_const": true,
            "format": "c4 (LUT4)",
            "n_items": 2322576,
            "tensors": [{
                "shape": [
                    1524,
                    1524
                ],
                "name": "gemm_0_weights"
            }],
            "zeros": 82,
            "raw_fmt": "(LUT_FLOAT, 4 bit, C Size: 4 bits)",
            "c_mem_pool": "gemm_0_weights",
            "padded": true,
            "size": 2322576,
            "c_type": "const float",
            "name": "gemm_0_weights_array",
            "c_id": 4,
            "c_bits": 4,
            "c_size_in_byte": 1161352
        },
        {
            "mem_pool": "weights",
            "offset": 0,
            "is_const": true,
            "format": "float32",
            "n_items": 1524,
            "tensors": [{
                "shape": [1524],
                "name": "gemm_0_bias"
            }],
            "zeros": 0,
            "raw_fmt": "(FLOAT, 32 bit, C Size: 32 bits)",
            "c_mem_pool": "gemm_0_bias",
            "padded": true,
            "size": 1524,
            "c_type": "const float",
            "name": "gemm_0_bias_array",
            "c_id": 5,
            "c_bits": 32,
            "c_size_in_byte": 6096
        },
        {
            "mem_pool": "weights",
            "offset": 64,
            "is_const": true,
            "format": "c4 (LUT4)",
            "n_items": 390144,
            "tensors": [{
                "shape": [
                    1524,
                    256
                ],
                "name": "gemm_1_weights"
            }],
            "zeros": 9,
            "raw_fmt": "(LUT_FLOAT, 4 bit, C Size: 4 bits)",
            "c_mem_pool": "gemm_1_weights",
            "padded": true,
            "size": 390144,
            "c_type": "const float",
            "name": "gemm_1_weights_array",
            "c_id": 6,
            "c_bits": 4,
            "c_size_in_byte": 195136
        },
        {
            "mem_pool": "weights",
            "offset": 0,
            "is_const": true,
            "format": "float32",
            "n_items": 256,
            "tensors": [{
                "shape": [256],
                "name": "gemm_1_bias"
            }],
            "zeros": 0,
            "raw_fmt": "(FLOAT, 32 bit, C Size: 32 bits)",
            "c_mem_pool": "gemm_1_bias",
            "padded": true,
            "size": 256,
            "c_type": "const float",
            "name": "gemm_1_bias_array",
            "c_id": 7,
            "c_bits": 32,
            "c_size_in_byte": 1024
        },
        {
            "mem_pool": "activations",
            "offset": 0,
            "is_const": false,
            "format": "float32",
            "n_items": 1524,
            "tensors": [{
                "shape": [
                    1,
                    1524
                ],
                "name": "serving_default_dense_input0_output"
            }],
            "raw_fmt": "(FLOAT, 32 bit, C Size: 32 bits)",
            "c_mem_pool": "**default**",
            "padded": true,
            "size": 1524,
            "c_type": "float",
            "name": "serving_default_dense_input0_output_array",
            "c_id": 8,
            "c_bits": 32,
            "c_size_in_byte": 6096,
            "io_type": "input"
        },
        {
            "mem_pool": "weights",
            "offset": 0,
            "is_const": true,
            "format": "float32",
            "n_items": 32768,
            "tensors": [{
                "shape": [
                    256,
                    128
                ],
                "name": "gemm_2_weights"
            }],
            "zeros": 0,
            "raw_fmt": "(FLOAT, 32 bit, C Size: 32 bits)",
            "c_mem_pool": "gemm_2_weights",
            "padded": true,
            "size": 32768,
            "c_type": "const float",
            "name": "gemm_2_weights_array",
            "c_id": 9,
            "c_bits": 32,
            "c_size_in_byte": 131072
        },
        {
            "mem_pool": "activations",
            "offset": 6096,
            "is_const": false,
            "format": "float32",
            "n_items": 1524,
            "tensors": [{
                "shape": [
                    1,
                    1524
                ],
                "name": "gemm_0_output"
            }],
            "raw_fmt": "(FLOAT, 32 bit, C Size: 32 bits)",
            "c_mem_pool": "**default**",
            "padded": true,
            "size": 1524,
            "c_type": "float",
            "name": "gemm_0_output_array",
            "c_id": 10,
            "c_bits": 32,
            "c_size_in_byte": 6096
        },
        {
            "mem_pool": "weights",
            "offset": 0,
            "is_const": true,
            "format": "float32",
            "n_items": 128,
            "tensors": [{
                "shape": [128],
                "name": "gemm_2_bias"
            }],
            "zeros": 0,
            "raw_fmt": "(FLOAT, 32 bit, C Size: 32 bits)",
            "c_mem_pool": "gemm_2_bias",
            "padded": true,
            "size": 128,
            "c_type": "const float",
            "name": "gemm_2_bias_array",
            "c_id": 11,
            "c_bits": 32,
            "c_size_in_byte": 512
        },
        {
            "mem_pool": "activations",
            "offset": 0,
            "is_const": false,
            "format": "float32",
            "n_items": 1524,
            "tensors": [{
                "shape": [
                    1,
                    1524
                ],
                "name": "nl_0_nl_output"
            }],
            "raw_fmt": "(FLOAT, 32 bit, C Size: 32 bits)",
            "c_mem_pool": "**default**",
            "padded": true,
            "size": 1524,
            "c_type": "float",
            "name": "nl_0_nl_output_array",
            "c_id": 12,
            "c_bits": 32,
            "c_size_in_byte": 6096
        },
        {
            "mem_pool": "activations",
            "offset": 6096,
            "is_const": false,
            "format": "float32",
            "n_items": 256,
            "tensors": [{
                "shape": [
                    1,
                    256
                ],
                "name": "gemm_1_output"
            }],
            "raw_fmt": "(FLOAT, 32 bit, C Size: 32 bits)",
            "c_mem_pool": "**default**",
            "padded": true,
            "size": 256,
            "c_type": "float",
            "name": "gemm_1_output_array",
            "c_id": 13,
            "c_bits": 32,
            "c_size_in_byte": 1024
        },
        {
            "mem_pool": "activations",
            "offset": 0,
            "is_const": false,
            "format": "float32",
            "n_items": 256,
            "tensors": [{
                "shape": [
                    1,
                    256
                ],
                "name": "nl_1_nl_output"
            }],
            "raw_fmt": "(FLOAT, 32 bit, C Size: 32 bits)",
            "c_mem_pool": "**default**",
            "padded": true,
            "size": 256,
            "c_type": "float",
            "name": "nl_1_nl_output_array",
            "c_id": 14,
            "c_bits": 32,
            "c_size_in_byte": 1024
        },
        {
            "mem_pool": "weights",
            "offset": 0,
            "is_const": true,
            "format": "float32",
            "n_items": 12,
            "tensors": [{
                "shape": [12],
                "name": "gemm_3_bias"
            }],
            "zeros": 0,
            "raw_fmt": "(FLOAT, 32 bit, C Size: 32 bits)",
            "c_mem_pool": "gemm_3_bias",
            "padded": true,
            "size": 12,
            "c_type": "const float",
            "name": "gemm_3_bias_array",
            "c_id": 15,
            "c_bits": 32,
            "c_size_in_byte": 48
        },
        {
            "mem_pool": "activations",
            "offset": 1024,
            "is_const": false,
            "format": "float32",
            "n_items": 128,
            "tensors": [{
                "shape": [
                    1,
                    128
                ],
                "name": "gemm_2_output"
            }],
            "raw_fmt": "(FLOAT, 32 bit, C Size: 32 bits)",
            "c_mem_pool": "**default**",
            "padded": true,
            "size": 128,
            "c_type": "float",
            "name": "gemm_2_output_array",
            "c_id": 16,
            "c_bits": 32,
            "c_size_in_byte": 512
        }
    ],
    "c_activations_count": 1,
    "date_time": "Tue Mar 26 09:06:33 2024",
    "model_name": "node_03_25_120900_ann_1524",
    "tool_version": {
        "major": 1,
        "minor": 7,
        "micro": 0
    },
    "c_intq_n": 0,
    "stm_ai_version": {
        "major": 8,
        "minor": 1,
        "micro": 0,
        "extra": "19520"
    },
    "model_fmt": "float",
    "c_weights_count": 8,
    "weights": {
        "gemm_0_bias_array": {
            "buffer_data_size": 6096,
            "buffer_crc": 0,
            "pool_size": 6096,
            "buffer_c_type": "u64",
            "buffer_c_name": "s_ann_1524_gemm_0_bias_array_u64",
            "buffer_offsets": [{
                "lite_tag": null,
                "offset": 0,
                "size": 6096,
                "start_offset": 0,
                "buffer_name": "gemm_0_bias_array"
            }],
            "buffer_c_name_addr": "s_ann_1524_gemm_0_bias_array_u64",
            "buffer_c_count": 762,
            "pool_id": 2,
            "buffer_c_data": []
        },
        "gemm_2_weights_array": {
            "buffer_data_size": 131072,
            "buffer_crc": 0,
            "pool_size": 131072,
            "buffer_c_type": "u64",
            "buffer_c_name": "s_ann_1524_gemm_2_weights_array_u64",
            "buffer_offsets": [{
                "lite_tag": null,
                "offset": 0,
                "size": 131072,
                "start_offset": 0,
                "buffer_name": "gemm_2_weights_array"
            }],
            "buffer_c_name_addr": "s_ann_1524_gemm_2_weights_array_u64",
            "buffer_c_count": 16384,
            "pool_id": 5,
            "buffer_c_data": []
        },
        "gemm_1_bias_array": {
            "buffer_data_size": 1024,
            "buffer_crc": 0,
            "pool_size": 1024,
            "buffer_c_type": "u64",
            "buffer_c_name": "s_ann_1524_gemm_1_bias_array_u64",
            "buffer_offsets": [{
                "lite_tag": null,
                "offset": 0,
                "size": 1024,
                "start_offset": 0,
                "buffer_name": "gemm_1_bias_array"
            }],
            "buffer_c_name_addr": "s_ann_1524_gemm_1_bias_array_u64",
            "buffer_c_count": 128,
            "pool_id": 4,
            "buffer_c_data": []
        },
        "gemm_3_weights_array": {
            "buffer_data_size": 6144,
            "buffer_crc": 0,
            "pool_size": 6144,
            "buffer_c_type": "u64",
            "buffer_c_name": "s_ann_1524_gemm_3_weights_array_u64",
            "buffer_offsets": [{
                "lite_tag": null,
                "offset": 0,
                "size": 6144,
                "start_offset": 0,
                "buffer_name": "gemm_3_weights_array"
            }],
            "buffer_c_name_addr": "s_ann_1524_gemm_3_weights_array_u64",
            "buffer_c_count": 768,
            "pool_id": 0,
            "buffer_c_data": []
        },
        "gemm_2_bias_array": {
            "buffer_data_size": 512,
            "buffer_crc": 0,
            "pool_size": 512,
            "buffer_c_type": "u64",
            "buffer_c_name": "s_ann_1524_gemm_2_bias_array_u64",
            "buffer_offsets": [{
                "lite_tag": null,
                "offset": 0,
                "size": 512,
                "start_offset": 0,
                "buffer_name": "gemm_2_bias_array"
            }],
            "buffer_c_name_addr": "s_ann_1524_gemm_2_bias_array_u64",
            "buffer_c_count": 64,
            "pool_id": 6,
            "buffer_c_data": []
        },
        "gemm_3_bias_array": {
            "buffer_data_size": 48,
            "buffer_crc": 0,
            "pool_size": 48,
            "buffer_c_type": "u64",
            "buffer_c_name": "s_ann_1524_gemm_3_bias_array_u64",
            "buffer_offsets": [{
                "lite_tag": null,
                "offset": 0,
                "size": 48,
                "start_offset": 0,
                "buffer_name": "gemm_3_bias_array"
            }],
            "buffer_c_name_addr": "s_ann_1524_gemm_3_bias_array_u64",
            "buffer_c_count": 6,
            "pool_id": 7,
            "buffer_c_data": []
        },
        "gemm_0_weights_array": {
            "buffer_data_size": 1161352,
            "buffer_crc": 0,
            "pool_size": 1161352,
            "buffer_c_type": "u64",
            "buffer_c_name": "s_ann_1524_gemm_0_weights_array_u64",
            "buffer_offsets": [{
                "lite_tag": null,
                "offset": 64,
                "size": 1161352,
                "start_offset": 0,
                "buffer_name": "gemm_0_weights_array"
            }],
            "buffer_c_name_addr": "s_ann_1524_gemm_0_weights_array_u64",
            "buffer_c_count": 145169,
            "pool_id": 1,
            "buffer_c_data": []
        },
        "gemm_1_weights_array": {
            "buffer_data_size": 195136,
            "buffer_crc": 0,
            "pool_size": 195136,
            "buffer_c_type": "u64",
            "buffer_c_name": "s_ann_1524_gemm_1_weights_array_u64",
            "buffer_offsets": [{
                "lite_tag": null,
                "offset": 64,
                "size": 195136,
                "start_offset": 0,
                "buffer_name": "gemm_1_weights_array"
            }],
            "buffer_c_name_addr": "s_ann_1524_gemm_1_weights_array_u64",
            "buffer_c_count": 24392,
            "pool_id": 3,
            "buffer_c_data": []
        }
    },
    "memory_footprint": {
        "kernel_ram": 2480,
        "kernel_flash": 14892,
        "io": [
            0,
            0
        ],
        "series": "generic",
        "activations": 12192,
        "weights": 1501384
    },
    "version": "1.2",
    "tool_api_version": {
        "major": 1,
        "minor": 5,
        "micro": 0
    },
    "model_signature": "ce64cfa73903de9a131364193b190964",
    "params_alignment": 4,
    "activations": {"heap_overlay_pool": {
        "buffer_data_size": 0,
        "pool_size": 12192,
        "buffer_c_name": "NULL",
        "buffer_offsets": [
            {
                "lite_tag": null,
                "offset": 0,
                "size": 6096,
                "start_offset": 0,
                "buffer_name": "serving_default_dense_input0_output_array"
            },
            {
                "lite_tag": null,
                "offset": 6096,
                "size": 6096,
                "start_offset": 6096,
                "buffer_name": "gemm_0_output_array"
            },
            {
                "lite_tag": null,
                "offset": 0,
                "size": 6096,
                "start_offset": 0,
                "buffer_name": "nl_0_nl_output_array"
            },
            {
                "lite_tag": null,
                "offset": 6096,
                "size": 1024,
                "start_offset": 6096,
                "buffer_name": "gemm_1_output_array"
            },
            {
                "lite_tag": null,
                "offset": 0,
                "size": 1024,
                "start_offset": 0,
                "buffer_name": "nl_1_nl_output_array"
            },
            {
                "lite_tag": null,
                "offset": 1024,
                "size": 512,
                "start_offset": 1024,
                "buffer_name": "gemm_2_output_array"
            },
            {
                "lite_tag": null,
                "offset": 0,
                "size": 512,
                "start_offset": 0,
                "buffer_name": "nl_2_nl_output_array"
            },
            {
                "lite_tag": null,
                "offset": 512,
                "size": 48,
                "start_offset": 512,
                "buffer_name": "gemm_3_output_array"
            },
            {
                "lite_tag": null,
                "offset": 0,
                "size": 48,
                "start_offset": 0,
                "buffer_name": "nl_4_output_array"
            }
        ],
        "buffer_c_name_addr": "NULL",
        "pool_id": 0
    }},
    "c_arrays_n": 17,
    "c_name": "ann_1524",
    "memory_pools": []
}